lstmAtten_datautils_J/__init__.py
lstmAtten_datautils_J/base_Conf.py
lstmAtten_datautils_J/data_loader.py
lstmAtten_datautils_J/process.py
lstmatten_datautils_j-1.1.1.dist-info/licenses/LICENSE
tests/__init__.py
tests/test_datautils.py
lstmatten_datautils_j-1.1.1.dist-info/METADATA
lstmatten_datautils_j-1.1.1.dist-info/WHEEL
lstmatten_datautils_j-1.1.1.dist-info/top_level.txt
lstmatten_datautils_j-1.1.1.dist-info/RECORD
